KTLib/KTLib.py
KTLib/__init__.py
Tello/Tello.py
Tello/__init__.py
KTLib-0.0.6.dist-info/LICENSE
KTLib-0.0.6.dist-info/METADATA
KTLib-0.0.6.dist-info/WHEEL
KTLib-0.0.6.dist-info/top_level.txt
KTLib-0.0.6.dist-info/RECORD
